jenius_mcp.py
iflow_mcp_jenius_mcp_smart_device-0.1.0.dist-info/licenses/LICENSE
iflow_mcp_jenius_mcp_smart_device-0.1.0.dist-info/licenses/NOTICE
tools/__init__.py
tools/common.py
tools/mcp/fan.py
tools/mcp/roborock_t7.py
tools/mcp/xiaomi_air_purifier.py
tools/mcp/xiaomi_speaker.py
tools/mcp/xiaomi_surveillance.py
utils/__init__.py
utils/error.py
utils/logger.py
iflow_mcp_jenius_mcp_smart_device-0.1.0.dist-info/METADATA
iflow_mcp_jenius_mcp_smart_device-0.1.0.dist-info/WHEEL
iflow_mcp_jenius_mcp_smart_device-0.1.0.dist-info/entry_points.txt
iflow_mcp_jenius_mcp_smart_device-0.1.0.dist-info/top_level.txt
iflow_mcp_jenius_mcp_smart_device-0.1.0.dist-info/RECORD
