Metadata-Version: 2.4
Name: iflow-mcp_jenius-mcp-smart-device
Version: 0.1.0
Summary: Jenius Smart Home Device Control MCP Server
Requires-Python: >=3.12
License-File: LICENSE
License-File: NOTICE
Requires-Dist: mcp[cli]>=1.9.4
Requires-Dist: pydantic>=2.11.7
Requires-Dist: pyyaml>=6.0.2
Requires-Dist: requests>=2.32.4
Requires-Dist: python-dotenv>=1.0.0
Requires-Dist: colorlog>=6.9.0
Dynamic: license-file
